battle_simulation/__init__.py
battle_simulation/core.py
battle_simulation/init__.py
battle_simulation/utils.py
battle_simulation/models/optimized_battle_model.pkl
battle_simulation/models/scaler.pkl
battle_simulation-1.0.7.dist-info/METADATA
battle_simulation-1.0.7.dist-info/WHEEL
battle_simulation-1.0.7.dist-info/top_level.txt
battle_simulation-1.0.7.dist-info/RECORD
